LICENSE
MANIFEST.in
README.md
VERSION
requirements.txt
setup.py
texta_mlp/__init__.py
texta_mlp/document.py
texta_mlp/entity_mapper.py
texta_mlp/exceptions.py
texta_mlp/fact.py
texta_mlp/mlp.py
texta_mlp/parsers.py
texta_mlp/russian_transliterator.py
texta_mlp/settings.py
texta_mlp/utils.py
texta_mlp.egg-info/PKG-INFO
texta_mlp.egg-info/SOURCES.txt
texta_mlp.egg-info/dependency_links.txt
texta_mlp.egg-info/requires.txt
texta_mlp.egg-info/top_level.txt