Metadata-Version: 2.1
Name: texta-mlp
Version: 1.15.6
Summary: TEXTA Multilingual Processor (MLP)
Home-page: https://git.texta.ee/texta/texta-mlp-python
Author: TEXTA
Author-email: info@texta.ee
License: GPLv3
Platform: UNKNOWN
